blendmodes/__init__.py
blendmodes/blend.py
blendmodes/blendtype.py
blendmodes-2024.1.1.dist-info/LICENSE.md
blendmodes-2024.1.1.dist-info/METADATA
blendmodes-2024.1.1.dist-info/WHEEL
blendmodes-2024.1.1.dist-info/RECORD
