Metadata-Version: 2.1
Name: blendmodes
Version: 2024.1.1
Summary: Use this module to apply a number of blending modes to a background and foreground image
Home-page: https://github.com/FHPythonUtils/BlendModes
License: MIT
Author: FredHappyface
Requires-Python: >=3.9,<4.0
Classifier: Development Status :: 5 - Production/Stable
Classifier: Intended Audience :: Developers
Classifier: Intended Audience :: Education
Classifier: License :: OSI Approved :: MIT License
Classifier: Natural Language :: English
Classifier: Operating System :: OS Independent
Classifier: Programming Language :: Python :: 3
Classifier: Programming Language :: Python :: 3.9
Classifier: Programming Language :: Python :: 3.10
Classifier: Programming Language :: Python :: 3.11
Classifier: Programming Language :: Python :: 3.12
Classifier: Programming Language :: Python :: Implementation :: CPython
Classifier: Topic :: Multimedia :: Graphics
Classifier: Topic :: Software Development :: Libraries :: Python Modules
Classifier: Topic :: Utilities
Requires-Dist: Pillow (>=10.2.0,<11)
Requires-Dist: aenum (>=3.1.15,<4)
Requires-Dist: numpy (>=1.26.4,<2)
Project-URL: Documentation, https://github.com/FHPythonUtils/BlendModes/blob/master/README.md
Project-URL: Repository, https://github.com/FHPythonUtils/BlendModes
